parrottools/__init__.py
parrottools/__version__.py
parrottools/py.typed
parrottools/events/__init__.py
parrottools/events/publisher.py
parrottools/logging/__init__.py
parrottools/logging/configure.py
parrottools-0.2.18.dist-info/METADATA
parrottools-0.2.18.dist-info/WHEEL
parrottools-0.2.18.dist-info/top_level.txt
parrottools-0.2.18.dist-info/RECORD
