Metadata-Version: 2.4
Name: parrottools
Version: 0.2.18
Summary: Collection of common utilities.
Home-page: https://github.com/parrot-com/parrottools
Author: Parrot
Maintainer: Parrot
Project-URL: Source Code, https://github.com/parrot-com/parrottools
Keywords: observability,logging
Classifier: Programming Language :: Python :: 3
Classifier: Programming Language :: Python :: 3.6
Classifier: Programming Language :: Python :: 3.7
Classifier: Programming Language :: Python :: 3.8
Classifier: Programming Language :: Python :: 3.9
Requires-Python: >=3.6
Requires-Dist: structlog~=24.1.0
Requires-Dist: sentry-sdk<3,>=1
Requires-Dist: contextvars~=2.4; python_version < "3.7"
Requires-Dist: rich~=13.7.1
Provides-Extra: events
Requires-Dist: boto3>=1.18.11; extra == "events"
Requires-Dist: protobuf>=3.17.3; extra == "events"
Requires-Dist: parrotschemas~=0.1.4; extra == "events"
Provides-Extra: tests
Requires-Dist: pytest>=6.2.1; extra == "tests"
Requires-Dist: freezegun==1.1.0; extra == "tests"
Provides-Extra: dev
Requires-Dist: pytest>=6.2.1; extra == "dev"
Requires-Dist: pre-commit>=2.9.3; extra == "dev"
Dynamic: author
Dynamic: classifier
Dynamic: description
Dynamic: description-content-type
Dynamic: home-page
Dynamic: keywords
Dynamic: maintainer
Dynamic: project-url
Dynamic: provides-extra
Dynamic: requires-dist
Dynamic: requires-python
Dynamic: summary
